enterprise_scheduler/__init__.py
enterprise_scheduler/executor.py
enterprise_scheduler/kernel_client.py
enterprise_scheduler/scheduler.py
enterprise_scheduler/scheduler_application.py
enterprise_scheduler/scheduler_resource.py
enterprise_scheduler/util.py
enterprise_scheduler/resources/ffdl/README.md
enterprise_scheduler/resources/ffdl/run_notebook.py
enterprise_scheduler/resources/ffdl/start.sh
enterprise_scheduler-0.1.0.dev2.dist-info/DESCRIPTION.rst
enterprise_scheduler-0.1.0.dev2.dist-info/METADATA
enterprise_scheduler-0.1.0.dev2.dist-info/RECORD
enterprise_scheduler-0.1.0.dev2.dist-info/WHEEL
enterprise_scheduler-0.1.0.dev2.dist-info/entry_points.txt
enterprise_scheduler-0.1.0.dev2.dist-info/metadata.json
enterprise_scheduler-0.1.0.dev2.dist-info/top_level.txt
